file_config/__init__.py
file_config/__version__.py
file_config/_file_config.py
file_config/constants.py
file_config/schema_builder.py
file_config/utils.py
file_config/contrib/__init__.py
file_config/contrib/ini_parser.py
file_config/contrib/xml_parser.py
file_config/handlers/__init__.py
file_config/handlers/_common.py
file_config/handlers/ini.py
file_config/handlers/json.py
file_config/handlers/msgpack.py
file_config/handlers/pickle.py
file_config/handlers/toml.py
file_config/handlers/xml.py
file_config/handlers/yaml.py
file_config-1.0.0.dist-info/LICENSE
file_config-1.0.0.dist-info/METADATA
file_config-1.0.0.dist-info/WHEEL
file_config-1.0.0.dist-info/top_level.txt
file_config-1.0.0.dist-info/zip-safe
file_config-1.0.0.dist-info/RECORD
