Metadata-Version: 2.1
Name: file-config
Version: 1.0.0
Summary: An attrs based configuration file abstraction
Home-page: https://github.com/stephen-bunn/file-config
Author: Stephen Bunn
Author-email: stephen@bunn.io
License: ISC License
Keywords: config,file,toml,json,yaml,msgpack,pickle,xml,ini,attrs
Platform: any
Classifier: Development Status :: 5 - Production/Stable
Classifier: Programming Language :: Python :: 3.6
Classifier: Programming Language :: Python :: 3.7
Classifier: License :: OSI Approved :: ISC License (ISCL)
Classifier: Intended Audience :: Developers
Classifier: Operating System :: POSIX
Classifier: Operating System :: MacOS :: MacOS X
Classifier: Operating System :: Microsoft :: Windows
Classifier: Natural Language :: English
Classifier: Topic :: Software Development :: Libraries :: Python Modules
Requires-Python: >=3.6
Requires-Dist: attrs
Requires-Dist: jsonschema
Provides-Extra: docs
Requires-Dist: sphinx ; extra == 'docs'
Provides-Extra: lxml
Requires-Dist: lxml ; extra == 'lxml'
Requires-Dist: defusedxml ; extra == 'lxml'
Provides-Extra: msgpack
Requires-Dist: msgpack ; extra == 'msgpack'
Provides-Extra: python_rapidjson
Requires-Dist: python-rapidjson ; extra == 'python_rapidjson'
Provides-Extra: pytoml
Requires-Dist: pytoml ; extra == 'pytoml'
Provides-Extra: pyyaml
Requires-Dist: pyyaml ; extra == 'pyyaml'
Provides-Extra: test
Requires-Dist: isort ; extra == 'test'
Requires-Dist: flake8 ; extra == 'test'
Requires-Dist: pytest ; extra == 'test'
Requires-Dist: pytest-flake8 ; extra == 'test'
Requires-Dist: pytest-sugar ; extra == 'test'
Requires-Dist: pytest-xdist ; extra == 'test'
Requires-Dist: pytest-cov ; extra == 'test'
Requires-Dist: hypothesis ; extra == 'test'
Requires-Dist: codecov ; extra == 'test'
Requires-Dist: codacy-coverage ; extra == 'test'
Requires-Dist: coverage ; extra == 'test'
Requires-Dist: readme-renderer ; extra == 'test'
Requires-Dist: check-manifest ; extra == 'test'
Requires-Dist: python-rapidjson ; extra == 'test'
Requires-Dist: ujson ; extra == 'test'
Requires-Dist: toml ; extra == 'test'
Requires-Dist: tomlkit ; extra == 'test'
Requires-Dist: pytoml ; extra == 'test'
Requires-Dist: pyyaml ; extra == 'test'
Requires-Dist: msgpack ; extra == 'test'
Requires-Dist: lxml ; extra == 'test'
Requires-Dist: defusedxml ; extra == 'test'
Provides-Extra: toml
Requires-Dist: toml ; extra == 'toml'
Provides-Extra: tomlkit
Requires-Dist: tomlkit ; extra == 'tomlkit'
Provides-Extra: ujson
Requires-Dist: ujson ; extra == 'ujson'
